jettie/__init__.py
jettie-0.1.dist-info/DESCRIPTION.rst
jettie-0.1.dist-info/METADATA
jettie-0.1.dist-info/RECORD
jettie-0.1.dist-info/WHEEL
jettie-0.1.dist-info/metadata.json
jettie-0.1.dist-info/top_level.txt
